shipyard_bigquery/__init__.py
shipyard_bigquery/bigquery.py
shipyard_bigquery/cli/__init__.py
shipyard_bigquery/cli/authtest.py
shipyard_bigquery/cli/download.py
shipyard_bigquery/cli/download_to_gcs.py
shipyard_bigquery/cli/execute_query.py
shipyard_bigquery/cli/upload.py
shipyard_bigquery/utils/creds.py
shipyard_bigquery/utils/exceptions.py
shipyard_bigquery-0.3.1.dist-info/METADATA
shipyard_bigquery-0.3.1.dist-info/WHEEL
shipyard_bigquery-0.3.1.dist-info/top_level.txt
shipyard_bigquery-0.3.1.dist-info/RECORD
