Metadata-Version: 2.4
Name: shipyard-bigquery
Version: 0.3.1
Summary: A local client for connecting to and working with Google BigQuery
Requires-Python: >=3.11
Requires-Dist: db-dtypes>=1.4.2
Requires-Dist: google-auth>=2.39.0
Requires-Dist: google-auth-httplib2>=0.2.0
Requires-Dist: google-auth-oauthlib>=1.2.2
Requires-Dist: google-cloud-bigquery>=3.31.0
Requires-Dist: pandas>=2.2.3
Requires-Dist: shipyard-bp-utils>=1.3.3a1
Requires-Dist: shipyard-templates>=0.9.0
